odoo/addons/hr_timesheet_role/README.rst
odoo/addons/hr_timesheet_role/__init__.py
odoo/addons/hr_timesheet_role/__manifest__.py
odoo/addons/hr_timesheet_role/i18n/de.po
odoo/addons/hr_timesheet_role/i18n/es.po
odoo/addons/hr_timesheet_role/i18n/fr.po
odoo/addons/hr_timesheet_role/i18n/hr_timesheet_role.pot
odoo/addons/hr_timesheet_role/i18n/it.po
odoo/addons/hr_timesheet_role/i18n/pt.po
odoo/addons/hr_timesheet_role/models/__init__.py
odoo/addons/hr_timesheet_role/models/account_analytic_line.py
odoo/addons/hr_timesheet_role/models/project_project.py
odoo/addons/hr_timesheet_role/models/res_company.py
odoo/addons/hr_timesheet_role/models/res_config_settings.py
odoo/addons/hr_timesheet_role/readme/CONTRIBUTORS.rst
odoo/addons/hr_timesheet_role/readme/DESCRIPTION.rst
odoo/addons/hr_timesheet_role/report/report_timesheet_templates.xml
odoo/addons/hr_timesheet_role/static/description/icon.png
odoo/addons/hr_timesheet_role/static/description/index.html
odoo/addons/hr_timesheet_role/tests/__init__.py
odoo/addons/hr_timesheet_role/tests/test_hr_timesheet_role.py
odoo/addons/hr_timesheet_role/views/account_analytic_line.xml
odoo/addons/hr_timesheet_role/views/project_portal_templates.xml
odoo/addons/hr_timesheet_role/views/project_project.xml
odoo/addons/hr_timesheet_role/views/project_task.xml
odoo/addons/hr_timesheet_role/views/res_config_settings.xml
odoo13_addon_hr_timesheet_role-13.0.1.0.1.dev8.dist-info/METADATA
odoo13_addon_hr_timesheet_role-13.0.1.0.1.dev8.dist-info/WHEEL
odoo13_addon_hr_timesheet_role-13.0.1.0.1.dev8.dist-info/top_level.txt
odoo13_addon_hr_timesheet_role-13.0.1.0.1.dev8.dist-info/RECORD
